{"nodes": [{"id": "c_wsgta_universal_or_strategy_src_v12_002_properties_cs", "label": "V12_002.Properties.cs", "file_type": "code", "source_file": "C:\\WSGTA\\universal-or-strategy\\src\\V12_002.Properties.cs", "source_location": "L1"}, {"id": "v12_002_properties_ninjatrader_ninjascript_strategies", "label": "NinjaTrader.NinjaScript.Strategies", "file_type": "code", "source_file": "C:\\WSGTA\\universal-or-strategy\\src\\V12_002.Properties.cs", "source_location": "L22"}, {"id": "v12_002_properties_v12_002", "label": "V12_002", "file_type": "code", "source_file": "C:\\WSGTA\\universal-or-strategy\\src\\V12_002.Properties.cs", "source_location": "L24"}, {"id": "strategy", "label": "Strategy", "file_type": "code", "source_file": "", "source_location": ""}], "edges": [{"source": "c_wsgta_universal_or_strategy_src_v12_002_properties_cs", "target": "system", "relation": "imports", "confidence": "EXTRACTED", "source_file": "C:\\WSGTA\\universal-or-strategy\\src\\V12_002.Properties.cs", "source_location": "L1", "weight": 1.0}, {"source": "c_wsgta_universal_or_strategy_src_v12_002_properties_cs", "target": "generic", "relation": "imports", "confidence": "EXTRACTED", "source_file": "C:\\WSGTA\\universal-or-strategy\\src\\V12_002.Properties.cs", "source_location": "L2", "weight": 1.0}, {"source": "c_wsgta_universal_or_strategy_src_v12_002_properties_cs", "target": "componentmodel", "relation": "imports", "confidence": "EXTRACTED", "source_file": "C:\\WSGTA\\universal-or-strategy\\src\\V12_002.Properties.cs", "source_location": "L3", "weight": 1.0}, {"source": "c_wsgta_universal_or_strategy_src_v12_002_properties_cs", "target": "dataannotations", "relation": "imports", "confidence": "EXTRACTED", "source_file": "C:\\WSGTA\\universal-or-strategy\\src\\V12_002.Properties.cs", "source_location": "L4", "weight": 1.0}, {"source": "c_wsgta_universal_or_strategy_src_v12_002_properties_cs", "target": "linq", "relation": "imports", "confidence": "EXTRACTED", "source_file": "C:\\WSGTA\\universal-or-strategy\\src\\V12_002.Properties.cs", "source_location": "L5", "weight": 1.0}, {"source": "c_wsgta_universal_or_strategy_src_v12_002_properties_cs", "target": "text", "relation": "imports", "confidence": "EXTRACTED", "source_file": "C:\\WSGTA\\universal-or-strategy\\src\\V12_002.Properties.cs", "source_location": "L6", "weight": 1.0}, {"source": "c_wsgta_universal_or_strategy_src_v12_002_properties_cs", "target": "tasks", "relation": "imports", "confidence": "EXTRACTED", "source_file": "C:\\WSGTA\\universal-or-strategy\\src\\V12_002.Properties.cs", "source_location": "L7", "weight": 1.0}, {"source": "c_wsgta_universal_or_strategy_src_v12_002_properties_cs", "target": "windows", "relation": "imports", "confidence": "EXTRACTED", "source_file": "C:\\WSGTA\\universal-or-strategy\\src\\V12_002.Properties.cs", "source_location": "L8", "weight": 1.0}, {"source": "c_wsgta_universal_or_strategy_src_v12_002_properties_cs", "target": "input", "relation": "imports", "confidence": "EXTRACTED", "source_file": "C:\\WSGTA\\universal-or-strategy\\src\\V12_002.Properties.cs", "source_location": "L9", "weight": 1.0}, {"source": "c_wsgta_universal_or_strategy_src_v12_002_properties_cs", "target": "media", "relation": "imports", "confidence": "EXTRACTED", "source_file": "C:\\WSGTA\\universal-or-strategy\\src\\V12_002.Properties.cs", "source_location": "L10", "weight": 1.0}, {"source": "c_wsgta_universal_or_strategy_src_v12_002_properties_cs", "target": "serialization", "relation": "imports", "confidence": "EXTRACTED", "source_file": "C:\\WSGTA\\universal-or-strategy\\src\\V12_002.Properties.cs", "source_location": "L11", "weight": 1.0}, {"source": "c_wsgta_universal_or_strategy_src_v12_002_properties_cs", "target": "cbi", "relation": "imports", "confidence": "EXTRACTED", "source_file": "C:\\WSGTA\\universal-or-strategy\\src\\V12_002.Properties.cs", "source_location": "L12", "weight": 1.0}, {"source": "c_wsgta_universal_or_strategy_src_v12_002_properties_cs", "target": "gui", "relation": "imports", "confidence": "EXTRACTED", "source_file": "C:\\WSGTA\\universal-or-strategy\\src\\V12_002.Properties.cs", "source_location": "L13", "weight": 1.0}, {"source": "c_wsgta_universal_or_strategy_src_v12_002_properties_cs", "target": "chart", "relation": "imports", "confidence": "EXTRACTED", "source_file": "C:\\WSGTA\\universal-or-strategy\\src\\V12_002.Properties.cs", "source_location": "L14", "weight": 1.0}, {"source": "c_wsgta_universal_or_strategy_src_v12_002_properties_cs", "target": "tools", "relation": "imports", "confidence": "EXTRACTED", "source_file": "C:\\WSGTA\\universal-or-strategy\\src\\V12_002.Properties.cs", "source_location": "L15", "weight": 1.0}, {"source": "c_wsgta_universal_or_strategy_src_v12_002_properties_cs", "target": "data", "relation": "imports", "confidence": "EXTRACTED", "source_file": "C:\\WSGTA\\universal-or-strategy\\src\\V12_002.Properties.cs", "source_location": "L16", "weight": 1.0}, {"source": "c_wsgta_universal_or_strategy_src_v12_002_properties_cs", "target": "ninjascript", "relation": "imports", "confidence": "EXTRACTED", "source_file": "C:\\WSGTA\\universal-or-strategy\\src\\V12_002.Properties.cs", "source_location": "L17", "weight": 1.0}, {"source": "c_wsgta_universal_or_strategy_src_v12_002_properties_cs", "target": "drawingtools", "relation": "imports", "confidence": "EXTRACTED", "source_file": "C:\\WSGTA\\universal-or-strategy\\src\\V12_002.Properties.cs", "source_location": "L18", "weight": 1.0}, {"source": "c_wsgta_universal_or_strategy_src_v12_002_properties_cs", "target": "indicators", "relation": "imports", "confidence": "EXTRACTED", "source_file": "C:\\WSGTA\\universal-or-strategy\\src\\V12_002.Properties.cs", "source_location": "L19", "weight": 1.0}, {"source": "c_wsgta_universal_or_strategy_src_v12_002_properties_cs", "target": "strategies", "relation": "imports", "confidence": "EXTRACTED", "source_file": "C:\\WSGTA\\universal-or-strategy\\src\\V12_002.Properties.cs", "source_location": "L20", "weight": 1.0}, {"source": "c_wsgta_universal_or_strategy_src_v12_002_properties_cs", "target": "v12_002_properties_ninjatrader_ninjascript_strategies", "relation": "contains", "confidence": "EXTRACTED", "source_file": "C:\\WSGTA\\universal-or-strategy\\src\\V12_002.Properties.cs", "source_location": "L22", "weight": 1.0}, {"source": "c_wsgta_universal_or_strategy_src_v12_002_properties_cs", "target": "v12_002_properties_v12_002", "relation": "contains", "confidence": "EXTRACTED", "source_file": "C:\\WSGTA\\universal-or-strategy\\src\\V12_002.Properties.cs", "source_location": "L24", "weight": 1.0}, {"source": "v12_002_properties_v12_002", "target": "strategy", "relation": "inherits", "confidence": "EXTRACTED", "source_file": "C:\\WSGTA\\universal-or-strategy\\src\\V12_002.Properties.cs", "source_location": "L24", "weight": 1.0}], "raw_calls": []}